README.md
license.txt
setup.py
pro_video_ferramenta/__init__.py
pro_video_ferramenta/camera.py
pro_video_ferramenta/video.py
pro_video_ferramentas_Ronaldoo_2024_ds.egg-info/PKG-INFO
pro_video_ferramentas_Ronaldoo_2024_ds.egg-info/SOURCES.txt
pro_video_ferramentas_Ronaldoo_2024_ds.egg-info/dependency_links.txt
pro_video_ferramentas_Ronaldoo_2024_ds.egg-info/top_level.txt