Metadata-Version: 2.1
Name: pro-video-ferramentas-Ronaldoo-2024-ds
Version: 1.0
Summary: Este pacote irá fornecer ferramentas de processamento de video
Author: Ronaldo
Author-email: Ronaldo@gmail.com
Keywords: Camera,Video,Processamento
License-File: license.txt
